{
    "003-GOSTERgizle": 
    {
      "PLAYBUTON": "TRU",
      "ARABESKgizli": "TRU",
      "SOHBETgizli": "TRUE"
},  
    "003-STREAMURL": 
    {
        "KRALFM": "http://46.20.3.204/;"
}, 
    "001linkler":
      {        
        "TVLER": "https://dogus-live.daioncdn.net/kralpoptv/kralpoptv.m3u8",
        "RADYOLAR": "https://kralmedya.github.io/HTML/tadilat.html",        
        "LOBITV": "https://kralmedya.github.io/TVLER/KRALMEDYATV2.html",        
        "LOBISOHBET": "https://www5.cbox.ws/box/?boxid=951754&boxtag=02lobi",        
        "KRALTV": "https://dogus-live.daioncdn.net/kralpoptv/kralpoptv.m3u8",
        "ANASOHBET": "https://www5.cbox.ws/box/?boxid=952177&boxtag=001SHB",        
        "BIRAZOYUN": "https://kralmedya.github.io/HTML/BIRAZOYUN.html"
},
    "001metinler": 
    {
        "KAYANDUYURU": "         Uygulamanızın 2. versiyonuna Hoş Geldiniz! Eklenmesini istediğiniz Kameraları bize bildirebilirsiniz. Google Play'de, uygulamanızı 5 yıldız ve güzel yorumlarınızla değerlendirmeniz bizim için gerçekten çok önemlidir. Desteğiniz için çok teşekkür ederiz."
},
    "001sayaclar":
      {
        "ANASAYAC": "https://kralmedya.github.io/SAYACLAR/001sayac.html",
        "STREAMSAYAC": "https://kralmedya.github.io/SAYACLAR/001STREAMSAYAC.html"       
},
    "003-FOTOLAR": 
    {
        "ARABESK": "https://kralmedya.github.io/HTML/003-ARABESK.html"
        "SOHBET": "https://www5.cbox.ws/box/?boxid=913679&boxtag=KFMSHB"
}, 

    "003-REKLAMLAR": 
    
    {
        "BANNERANA"           : "ca-app-pub-3940256099942544/6300978111",
        "GECISANA"            : "ca-app-pub-3940256099942544/1033173712",
        "YERELANA"            : "ca-app-pub-3940256099942544/6300978111",
        "OPENANA"             : "ca-app-pub-3940256099942544/6300978111",
        "XXX"              : "ca-app-pub-3940256099942544/6300978111",
        "XXX"              : "ca-app-pub-3940256099942544/6300978111",
        "XXX"              : "ca-app-pub-3940256099942544/6300978111",
        "XXX"              : "ca-app-pub-3940256099942544/6300978111",
        "XXX"              : "ca-app-pub-3940256099942544/6300978111",
        "XXX"              : "ca-app-pub-3940256099942544/6300978111",
        "XXX"              : "ca-app-pub-3940256099942544/6300978111",
        "BANNERTEST"              : "ca-app-pub-3940256099942544/6300978111",
        "GECISTEST"              : "ca-app-pub-3940256099942544/1033173712",
        "YERELTEST"              : "ca-app-pub-3940256099942544/2247696110",
        "OPENTEST"              : "ca-app-pub-3940256099942544/9257395921"
}
}
