{
  "gizlibuton": 
    {
      "000goster": "true",
      "001tv": "true"
    },  
  "002": 
    {
        "002goster": "",
        "002gosterTEST": "true",      
        "BIRAZOYUN": "https://ferdimedya.com"
    },
  "002link":
      {
        "TVLER": "https://kralmedya.github.io/TVLER/KRALMEDYATV2.html",
        "KRALTVTV": "https://dogus-live.daioncdn.net/kralpoptv/kralpoptv.m3u8",        
        "KRALTVSOHBET": "https://www5.cbox.ws/box/?boxid=913679&boxtag=KFMSHB",        
        "BIRAZOYUN": "https://kralmedya.github.io/TVLER/BIRAZOYUN.html",
        "EFKARLOBI": "https://kralmedya.github.io/TVLER/KRALMEDYATV2.html",
        "LOBISOHBET": "https://www5.cbox.ws/box/?boxid=951754&boxtag=02lobi",
        "SAYAC": "https://kralmedya.github.io/SAYACLAR/002sayac.html"
}
}
